file_converter/__init__.py
file_converter/converter.py
json_csv_file_converter-0.1.dist-info/METADATA
json_csv_file_converter-0.1.dist-info/WHEEL
json_csv_file_converter-0.1.dist-info/top_level.txt
json_csv_file_converter-0.1.dist-info/RECORD
