Metadata-Version: 2.1
Name: json-csv-file-converter
Version: 0.1
Requires-Dist: boto3 >=1.34.78
Requires-Dist: requests >=2.31.0
